LICENSE
MANIFEST.in
README.md
setup.py
mpns/__init__.py
mpns/notification.py
python_mpns.egg-info/PKG-INFO
python_mpns.egg-info/SOURCES.txt
python_mpns.egg-info/dependency_links.txt
python_mpns.egg-info/requires.txt
python_mpns.egg-info/top_level.txt