Metadata-Version: 1.0
Name: python-mpns
Version: 0.1.3
Summary: Python module for Microsoft Push Notification Service (MPNS) for Windows Phone
Home-page: http://github.com/max-arnold/python-mpns
Author: Max Arnold
Author-email: arnold.maxim@gmail.com
License: BSD
Keywords: mobile push notification microsoft mpns windows phone
Platform: any
Classifier: Development Status :: 3 - Alpha
Classifier: Intended Audience :: Developers
Classifier: License :: OSI Approved :: BSD License
Classifier: Operating System :: OS Independent
Classifier: Topic :: Software Development :: Libraries :: Python Modules
Classifier: Topic :: Communications :: Telephony
Classifier: Topic :: Internet
